cmtt/__init__.py
cmtt/data/__init__.py
cmtt/data/data.json
cmtt/data/downloader.py
cmtt/preprocessing/__init__.py
cmtt/preprocessing/search.py
cmtt/preprocessing/sentence_piece_tokenizer/__init__.py
cmtt/preprocessing/sentence_piece_tokenizer/build_vocb.py
cmtt/preprocessing/sentence_piece_tokenizer/config.py
cmtt/preprocessing/sentence_piece_tokenizer/download_assets.py
cmtt/preprocessing/stemmer/__init__.py
cmtt/preprocessing/stemmer/stemmer.py
cmtt/preprocessing/tokenizer/__init__.py
cmtt/preprocessing/tokenizer/vocab.txt
cmtt/preprocessing/tokenizer/vocab_2.txt
cmtt/tasks/__init__.py
cmtt/tasks/LID/__init__.py
cmtt/tasks/LID/BiLSTM_LID/__init__.py
cmtt/tasks/NER/__init__.py
cmtt/tasks/NER/BiLSTM_NER/__init__.py
cmtt/tasks/POS/__init__.py
cmtt/tasks/POS/BiLSTM_POS/__init__.py
cmtt-0.8.0.data/data/cmtt/data/data.json
cmtt-0.8.0.data/data/cmtt/preprocessing/tokenizer/vocab.txt
cmtt-0.8.0.data/data/cmtt/preprocessing/tokenizer/vocab_2.txt
tests/__init__.py
tests/cmtt_tests.py
cmtt-0.8.0.dist-info/METADATA
cmtt-0.8.0.dist-info/WHEEL
cmtt-0.8.0.dist-info/dependency_links.txt
cmtt-0.8.0.dist-info/top_level.txt
cmtt-0.8.0.dist-info/RECORD
