Metadata-Version: 2.1
Name: cmtt
Version: 0.8.0
Summary: A library for processing Code Mixed Text. Still in development!
Home-page: https://cmtt.readthedocs.io/
Author: Reuben Devanesan
Author-email: reubendevanesan@gmail.com
License: MIT
Platform: UNKNOWN
Classifier: Intended Audience :: Developers
Classifier: License :: OSI Approved :: MIT License
Classifier: Programming Language :: Python
Classifier: Programming Language :: Python :: 3
Classifier: Programming Language :: Python :: 3.9
Classifier: Programming Language :: Python :: 3.10
Classifier: Operating System :: OS Independent
Requires-Dist: numpy
Requires-Dist: pandas
Requires-Dist: requests
Requires-Dist: tqdm
Requires-Dist: fastai (==1.0.57)
Requires-Dist: sentencepiece
Requires-Dist: torch (==1.8.0)
Requires-Dist: dill
Requires-Dist: torchtext (==0.9.0)
Requires-Dist: googletrans
